game_object_detection/__init__.py
game_object_detection/detector.py
game_object_detection/trainer.py
game_object_detection-1.0.0.dist-info/METADATA
game_object_detection-1.0.0.dist-info/WHEEL
game_object_detection-1.0.0.dist-info/top_level.txt
game_object_detection-1.0.0.dist-info/RECORD
