Metadata-Version: 2.4
Name: game-object-detection
Version: 1.0.0
Author: Alex
Author-email: thettboy11@gmail.com
Classifier: Programming Language :: Python :: 3
Classifier: License :: OSI Approved :: MIT License
Classifier: Operating System :: OS Independent
Requires-Python: >=3.8
Requires-Dist: torch>=1.9.0
Requires-Dist: ultralytics>=8.0.0
Requires-Dist: opencv-python>=4.5.0
Requires-Dist: numpy>=1.21.0
Requires-Dist: Pillow>=8.0.0
Requires-Dist: scikit-learn>=1.0.0
Requires-Dist: PyYAML>=6.0
Dynamic: author
Dynamic: author-email
Dynamic: classifier
Dynamic: description-content-type
Dynamic: requires-dist
Dynamic: requires-python
